apitree/__init__.py
apitree/ast_utils.py
apitree/conf_util.py
apitree/context.py
apitree/debug_utils.py
apitree/html_helper.py
apitree/import_utils.py
apitree/main.py
apitree/md_utils.py
apitree/signature_utils.py
apitree/structs.py
apitree/symbol_match.py
apitree/tree_extractor.py
apitree/writer.py
apitree/ext/auto_ref.py
apitree/ext/docstring.py
apitree/ext/github_link.py
apitree/templates/api.md
apitree/templates/attribute.md
apitree/templates/class.md
apitree/templates/function.md
apitree/templates/module.md
apitree/templates/type_alias.md
sphinx_apitree-1.6.2.dist-info/licenses/LICENSE
sphinx_apitree-1.6.2.dist-info/WHEEL
sphinx_apitree-1.6.2.dist-info/METADATA
sphinx_apitree-1.6.2.dist-info/RECORD
