Metadata-Version: 2.4
Name: sphinx-apitree
Version: 1.6.2
Summary: Sphinx extension to auto-generate API tree.
Keywords: sphinx,doc
Author-email: Conchylicultor <etiennefg.pot@mail.com>
Requires-Python: >=3.10
Classifier: Programming Language :: Python :: 3
Classifier: Programming Language :: Python :: 3 :: Only
Classifier: License :: OSI Approved :: Apache Software License
Classifier: Intended Audience :: Developers
License-File: LICENSE
Requires-Dist: etils[edc, enp, epath, epy, etree]
Requires-Dist: typing_extensions
Requires-Dist: pytest>=3.4 ; extra == "dev"
Requires-Dist: pytest-xdist ; extra == "dev"
Requires-Dist: pylint>=2.6.0 ; extra == "dev"
Requires-Dist: pyink ; extra == "dev"
Requires-Dist: sphinx-apitree[ext] ; extra == "dev"
Requires-Dist: etils[ecolab] ; extra == "dev"
Requires-Dist: sphinx ; extra == "ext"
Requires-Dist: myst_nb ; extra == "ext"
Requires-Dist: sphinx_book_theme ; extra == "ext"
Requires-Dist: sphinx-reredirects ; extra == "ext"
Project-URL: homepage, https://github.com/conchylicultor/sphinx-apitree
Project-URL: repository, https://github.com/conchylicultor/sphinx-apitree
Provides-Extra: dev
Provides-Extra: ext
